qwota_cli.py
qwota-0.0.2.dist-info/LICENSE
qwota-0.0.2.dist-info/METADATA
qwota-0.0.2.dist-info/WHEEL
qwota-0.0.2.dist-info/entry_points.txt
qwota-0.0.2.dist-info/top_level.txt
qwota-0.0.2.dist-info/RECORD
