Metadata-Version: 2.1
Name: qwota
Version: 0.0.2
Summary: Tool for checking OpenShift AppliedClusterQuotaResource
Home-page: https://github.com/hseljenes/qwota
Author: Henning Seljenes
Author-email: henning.seljenes@gmail.com
License: MIT
Platform: UNKNOWN
Classifier: Programming Language :: Python
Classifier: Operating System :: OS Independent
Requires-Python: >=3
License-File: LICENSE
Requires-Dist: openshift
